Metadata-Version: 1.0
Name: seq-io
Version: 0.10
Summary: Import .seq files into hyperspy
Home-page: https://github.com/CSSFrancis/SeqIO
Author: Carter Francis
Author-email: csfrancis@wisc.edu
License: MIT
Keywords: data analysis,diffraction,microscopy,electron diffraction,electron microscopy
Platform: UNKNOWN
